job13/__init__.py
job13/konversi_berat.py
job13/tebak_angka.py
pkg13-0.1.0.dist-info/METADATA
pkg13-0.1.0.dist-info/WHEEL
pkg13-0.1.0.dist-info/top_level.txt
pkg13-0.1.0.dist-info/RECORD
