Metadata-Version: 2.1
Name: pkg13
Version: 0.1.0
Summary: Learn to create python package
Author: Al (Aldo Ramadhana)
Author-email: <aldoramadhana852@gmail.com>
Keywords: python,guess,number,weight,conversion,guess number,weight conversion
Classifier: Development Status :: 1 - Planning
Classifier: Intended Audience :: Developers
Classifier: Programming Language :: Python :: 3
Classifier: Operating System :: Unix
Classifier: Operating System :: MacOS :: MacOS X
Classifier: Operating System :: Microsoft :: Windows
